Metadata-Version: 2.1
Name: SEAScope-env-OTC2023
Version: 1.5
Summary: Helper for installing the Python environment for the OTC 2023 interactive lectures based on SEAScope
Home-page: https://pypi.org/project/SEAScope-env-OTC2023/
Author: Sylvain Herlédan
Author-email: sylvain.herledan@oceandatalab.com
Project-URL: Homepage, https://oceantrainingcourse2023.esa.int/
Project-URL: Issues, https://forum.oceandatalab.com/seascope
License-File: COPYING
License-File: COPYING.LESSER
